better_input-1.0.0.dist-info/METADATA
better_input-1.0.0.dist-info/WHEEL
better_input/__init__.py
better_input/better_input.cp39-win_amd64.pyd
better_input-1.0.0.dist-info/RECORD
