Metadata-Version: 2.1
Name: better_input
Version: 1.0.0
Summary: Efficient high-speed improvement of Python's input systems (using Rust)
Author: Ifaz Ahmed <ifazahmed375@gmail.com>
Author-email: Ifaz Ahmed <ifazahmed375@gmail.com>
